ahbicht/__init__.py
ahbicht/condition_node_builder.py
ahbicht/condition_node_distinction.py
ahbicht/py.typed
ahbicht/utility_functions.py
ahbicht/content_evaluation/EvaluatingConditions.png
ahbicht/content_evaluation/__init__.py
ahbicht/content_evaluation/evaluationdatatypes.py
ahbicht/content_evaluation/evaluator_factory.py
ahbicht/content_evaluation/evaluators.py
ahbicht/content_evaluation/expression_check.py
ahbicht/content_evaluation/fc_evaluators.py
ahbicht/content_evaluation/german_strom_and_gas_tag.py
ahbicht/content_evaluation/rc_evaluators.py
ahbicht/content_evaluation/token_logic_provider.py
ahbicht/expressions/__init__.py
ahbicht/expressions/ahb_expression_evaluation.py
ahbicht/expressions/ahb_expression_parser.py
ahbicht/expressions/base_transformer.py
ahbicht/expressions/condition_expression_parser.py
ahbicht/expressions/condition_structure_with_more_than_one_condition.png
ahbicht/expressions/expression_builder.py
ahbicht/expressions/expression_resolver.py
ahbicht/expressions/format_constraint_expression_evaluation.py
ahbicht/expressions/hints_provider.py
ahbicht/expressions/package_expansion.py
ahbicht/expressions/requirement_constraint_expression_evaluation.py
ahbicht/expressions/sanitizer.py
ahbicht/json_serialization/__init__.py
ahbicht/json_serialization/tree_schema.py
ahbicht/models/__init__.py
ahbicht/models/categorized_key_extract.py
ahbicht/models/condition_node_type.py
ahbicht/models/condition_nodes.py
ahbicht/models/content_evaluation_result.py
ahbicht/models/enums.py
ahbicht/models/evaluation_results.py
ahbicht/models/mapping_results.py
ahbicht-1.0.0.dist-info/METADATA
ahbicht-1.0.0.dist-info/WHEEL
ahbicht-1.0.0.dist-info/licenses/LICENSE
ahbicht-1.0.0.dist-info/RECORD
