Metadata-Version: 2.4
Name: ahbicht
Version: 1.0.0
Summary: Python Library to parse AHB expressions.
Project-URL: Changelog, https://github.com/Hochfrequenz/ahbicht/releases
Project-URL: Homepage, https://github.com/Hochfrequenz/ahbicht
Project-URL: Documentation, https://ahbicht.readthedocs.io/en/latest/
Author-email: Annika Schlögl <annika.schloegl@hochfrequenz.de>
License: MIT
License-File: LICENSE
Keywords: AHB,Expressions,Parsing
Classifier: Development Status :: 4 - Beta
Classifier: Environment :: Console
Classifier: Intended Audience :: Developers
Classifier: License :: OSI Approved :: MIT License
Classifier: Operating System :: OS Independent
Classifier: Programming Language :: Python
Classifier: Programming Language :: Python :: 3 :: Only
Classifier: Programming Language :: Python :: 3.10
Classifier: Programming Language :: Python :: 3.11
Classifier: Programming Language :: Python :: 3.12
Classifier: Programming Language :: Python :: 3.13
Classifier: Programming Language :: Python :: 3.14
Requires-Python: >=3.10
Requires-Dist: efoli>=2.1.0
Requires-Dist: inject
Requires-Dist: lark>=1.1.4
Requires-Dist: pydantic>=2
Requires-Dist: pytz
Provides-Extra: coverage
Requires-Dist: coverage==7.10.7; extra == 'coverage'
Provides-Extra: dev
Requires-Dist: pip-tools; extra == 'dev'
Provides-Extra: docs
Requires-Dist: sphinx-rtd-theme==3.0.2; extra == 'docs'
Requires-Dist: sphinx==8.1.3; extra == 'docs'
Provides-Extra: formatting
Requires-Dist: black[jupyter]==25.9.0; extra == 'formatting'
Requires-Dist: isort==6.1.0; extra == 'formatting'
Provides-Extra: json-schemas
Provides-Extra: linting
Requires-Dist: pylint==3.3.9; extra == 'linting'
Provides-Extra: spellcheck
Requires-Dist: codespell==2.4.1; extra == 'spellcheck'
Provides-Extra: test-packaging
Requires-Dist: build==1.3.0; extra == 'test-packaging'
Requires-Dist: setuptools-scm==9.2.2; extra == 'test-packaging'
Requires-Dist: setuptools==80.9.0; extra == 'test-packaging'
Requires-Dist: twine==6.2.0; extra == 'test-packaging'
Provides-Extra: tests
Requires-Dist: pytest-asyncio==1.2.0; extra == 'tests'
Requires-Dist: pytest-datafiles==3.0.0; extra == 'tests'
Requires-Dist: pytest-mock==3.15.1; extra == 'tests'
Requires-Dist: pytest==8.4.2; extra == 'tests'
Provides-Extra: type-check
Requires-Dist: mypy[pydantic]==1.18.2; extra == 'type-check'
Requires-Dist: types-pytz==2025.2.0.20250809; extra == 'type-check'
